CHANGES.rst
CONTRIBUTORS.txt
LICENSE.txt
MANIFEST.in
README.rst
setup.py
django_mediamosa_tinymce.egg-info/PKG-INFO
django_mediamosa_tinymce.egg-info/SOURCES.txt
django_mediamosa_tinymce.egg-info/dependency_links.txt
django_mediamosa_tinymce.egg-info/not-zip-safe
django_mediamosa_tinymce.egg-info/pbr.json
django_mediamosa_tinymce.egg-info/requires.txt
django_mediamosa_tinymce.egg-info/top_level.txt
mediamosa_tinymce/__init__.py
mediamosa_tinymce/models.py
mediamosa_tinymce/urls.py
mediamosa_tinymce/views.py
mediamosa_tinymce/locale/nl/LC_MESSAGES/django.mo
mediamosa_tinymce/locale/nl/LC_MESSAGES/django.po
mediamosa_tinymce/static/js/jquery.idTabs.min.js
mediamosa_tinymce/static/js/mediamosa-player.js
mediamosa_tinymce/static/tiny_mce/plugins/mediamosa/editor_plugin.js
mediamosa_tinymce/static/tiny_mce/plugins/mediamosa/mediamosa-dialog.js
mediamosa_tinymce/static/tiny_mce/plugins/mediamosa/img/mediamosa.png
mediamosa_tinymce/static/tiny_mce/plugins/mediamosa/langs/en.js
mediamosa_tinymce/static/tiny_mce/plugins/mediamosa/langs/en_dlg.js
mediamosa_tinymce/static/tiny_mce/plugins/mediamosa/langs/nl.js
mediamosa_tinymce/static/tiny_mce/plugins/mediamosa/langs/nl_dlg.js
mediamosa_tinymce/templates/admin/mediamosa_tinymce_change_form.html
mediamosa_tinymce/templates/mediamosa_tinymce/tinymce_asset_dialog.html