Metadata-Version: 1.1
Name: django-mediamosa-tinymce
Version: 0.1.3
Summary: Django integration for mediamosa in TinyMCE.
Home-page: https://github.com/UGentPortaal/django-mediamosa-tinymce
Author: UGent Portaal Team
Author-email: portaal-tech@ugent.be
License: BSD
Platform: UNKNOWN
Classifier: Development Status :: 3 - Alpha
Classifier: Environment :: Web Environment
Classifier: Framework :: Django
Classifier: Intended Audience :: Developers
Classifier: License :: OSI Approved :: BSD License
Classifier: Operating System :: MacOS :: MacOS X
Classifier: Operating System :: Microsoft :: Windows
Classifier: Operating System :: POSIX
Classifier: Programming Language :: Python
Classifier: Topic :: Internet :: WWW/HTTP :: Dynamic Content
Classifier: Topic :: Multimedia :: Video
Classifier: Topic :: Software Development :: Libraries
Classifier: Topic :: Utilities
